pepmatch-0.9.5.dist-info/RECORD
pepmatch-0.9.5.dist-info/top_level.txt
pepmatch-0.9.5.dist-info/entry_points.txt
pepmatch-0.9.5.dist-info/WHEEL
pepmatch-0.9.5.dist-info/METADATA
pepmatch-0.9.5.dist-info/LICENSE
pepmatch/version.py
pepmatch/preprocessor.py
pepmatch/matcher.py
pepmatch/helpers.py
pepmatch/hamming.cpython-311-x86_64-linux-gnu.so
pepmatch/benchmarker.py
pepmatch/__init__.py
