Metadata-Version: 2.1
Name: pepmatch
Version: 0.9.5
Summary: Search tool for peptides and epitopes within a proteome, while considering potential residue substitutions.
Home-page: https://github.com/IEDB/PEPMatch
Author: Daniel Marrama
Author-email: dmarrama@lji.org
License-File: LICENSE
Requires-Dist: numpy >=1.18
Requires-Dist: pandas >=1.1
Requires-Dist: biopython >=1.5
Requires-Dist: python-Levenshtein >=0.11
Requires-Dist: openpyxl >=3.0.0
